django_oauth_usp/__init__.py
django_oauth_usp/accounts/__init__.py
django_oauth_usp/accounts/admin.py
django_oauth_usp/accounts/apps.py
django_oauth_usp/accounts/managers.py
django_oauth_usp/accounts/middleware.py
django_oauth_usp/accounts/migrations/0001_initial.py
django_oauth_usp/accounts/migrations/__init__.py
django_oauth_usp/accounts/models.py
django_oauth_usp/accounts/oauth.py
django_oauth_usp/accounts/templates/account_main.html
django_oauth_usp/accounts/templates/user.html
django_oauth_usp/accounts/tests/__init__.py
django_oauth_usp/accounts/tests/faker.py
django_oauth_usp/accounts/tests/mock.py
django_oauth_usp/accounts/tests/test_accounts_admin.py
django_oauth_usp/accounts/tests/test_accounts_manager.py
django_oauth_usp/accounts/tests/test_accounts_models.py
django_oauth_usp/accounts/tests/test_accounts_transform.py
django_oauth_usp/accounts/tests/test_accounts_views.py
django_oauth_usp/accounts/tests/test_oauth.py
django_oauth_usp/accounts/tests/test_user_middleware.py
django_oauth_usp/accounts/transform.py
django_oauth_usp/accounts/urls.py
django_oauth_usp/accounts/views.py
django_oauth_usp/settings.py
django_oauth_usp/urls.py
django_oauth_usp-1.2.2.dist-info/LICENSE
django_oauth_usp-1.2.2.dist-info/METADATA
django_oauth_usp-1.2.2.dist-info/WHEEL
django_oauth_usp-1.2.2.dist-info/RECORD
