Metadata-Version: 2.1
Name: django-oauth-usp
Version: 1.2.2
Summary: 
License: MIT
Author: Marcelo Schneider
Author-email: schenider.fei@gmail.com
Requires-Python: >=3.10,<4.0
Classifier: Environment :: Web Environment
Classifier: Framework :: Django
Classifier: Intended Audience :: Developers
Classifier: License :: OSI Approved :: MIT License
Classifier: Operating System :: OS Independent
Classifier: Programming Language :: Python :: 3
Classifier: Programming Language :: Python :: 3.10
Classifier: Programming Language :: Python :: 3.11
Classifier: Programming Language :: Python :: 3.7
Classifier: Programming Language :: Python :: 3.8
Classifier: Topic :: Internet :: WWW/HTTP
Classifier: Topic :: Internet :: WWW/HTTP :: Dynamic Content
Requires-Dist: authlib (>=1.2.1,<2.0.0)
Requires-Dist: requests (>=2.31.0,<3.0.0)
